{
  "dataset": "blobs",
  "algorithm": "meanshift",
  "params": {
    "bandwidth": 0.3
  },
  "labels": [
    54,
    175,
    77,
    138,
    34,
    22,
    146,
    1,
    6,
    37,
    44,
    130,
    105,
    132,
    93,
    111,
    86,
    177,
    39,
    50,
    81,
    47,
    114,
    95,
    11,
    10,
    94,
    3,
    73,
    45,
    23,
    132,
    65,
    66,
    10,
    24,
    14,
    82,
    8,
    157,
    99,
    12,
    33,
    85,
    126,
    108,
    43,
    113,
    37,
    11,
    167,
    139,
    40,
    22,
    115,
    20,
    17,
    39,
    35,
    76,
    58,
    15,
    37,
    4,
    30,
    100,
    68,
    172,
    43,
    35,
    80,
    36,
    90,
    4,
    19,
    74,
    84,
    24,
    0,
    50,
    22,
    13,
    25,
    45,
    59,
    76,
    74,
    71,
    44,
    17,
    5,
    147,
    62,
    1,
    0,
    171,
    131,
    14,
    48,
    55,
    44,
    9,
    41,
    103,
    26,
    18,
    7,
    179,
    89,
    27,
    56,
    75,
    164,
    26,
    3,
    102,
    6,
    8,
    98,
    23,
    32,
    12,
    25,
    14,
    154,
    108,
    31,
    24,
    56,
    26,
    57,
    0,
    122,
    21,
    28,
    5,
    3,
    5,
    123,
    6,
    22,
    153,
    112,
    14,
    1,
    40,
    58,
    7,
    18,
    50,
    152,
    25,
    44,
    63,
    15,
    5,
    18,
    97,
    10,
    98,
    92,
    8,
    79,
    9,
    36,
    2,
    61,
    148,
    75,
    59,
    90,
    16,
    32,
    8,
    38,
    20,
    48,
    101,
    22,
    145,
    48,
    57,
    64,
    32,
    149,
    11,
    127,
    60,
    32,
    68,
    69,
    165,
    55,
    53,
    20,
    143,
    15,
    16,
    103,
    34,
    86,
    84,
    91,
    39,
    61,
    26,
    159,
    30,
    13,
    5,
    96,
    67,
    97,
    51,
    15,
    53,
    16,
    38,
    18,
    28,
    119,
    19,
    27,
    7,
    61,
    45,
    20,
    35,
    25,
    6,
    24,
    14,
    49,
    56,
    54,
    37,
    134,
    34,
    13,
    0,
    62,
    169,
    140,
    43,
    8,
    4,
    29,
    136,
    85,
    24,
    17,
    133,
    65,
    17,
    116,
    9,
    5,
    32,
    67,
    14,
    135,
    15,
    27,
    20,
    151,
    21,
    43,
    20,
    0,
    23,
    15,
    66,
    42,
    96,
    7,
    66,
    89,
    0,
    39,
    158,
    64,
    31,
    0,
    2,
    53,
    17,
    29,
    57,
    14,
    52,
    52,
    48,
    51,
    29,
    176,
    124,
    38,
    63,
    142,
    42,
    52,
    3,
    78,
    30,
    83,
    77,
    1,
    36,
    82,
    42,
    91,
    8,
    41,
    78,
    29,
    100,
    5,
    108,
    9,
    110,
    70,
    109,
    121,
    71,
    8,
    4,
    144,
    59,
    27,
    160,
    3,
    4,
    125,
    39,
    28,
    54,
    2,
    51,
    4,
    12,
    63,
    0,
    19,
    49,
    1,
    20,
    102,
    128,
    120,
    152,
    37,
    41,
    36,
    71,
    76,
    99,
    58,
    46,
    173,
    2,
    42,
    19,
    162,
    21,
    72,
    0,
    163,
    14,
    0,
    3,
    2,
    21,
    0,
    1,
    11,
    44,
    38,
    13,
    8,
    75,
    21,
    150,
    46,
    88,
    40,
    156,
    7,
    23,
    3,
    22,
    5,
    62,
    87,
    83,
    168,
    36,
    31,
    7,
    65,
    46,
    104,
    155,
    22,
    51,
    6,
    79,
    35,
    26,
    34,
    35,
    161,
    2,
    107,
    25,
    7,
    31,
    7,
    19,
    0,
    33,
    28,
    87,
    74,
    68,
    81,
    47,
    23,
    95,
    7,
    117,
    118,
    101,
    88,
    174,
    3,
    1,
    12,
    92,
    7,
    141,
    59,
    9,
    27,
    41,
    129,
    151,
    36,
    170,
    47,
    29,
    14,
    54,
    49,
    93,
    52,
    10,
    9,
    67,
    16,
    0,
    38,
    60,
    52,
    0,
    33,
    13,
    64,
    80,
    53,
    45,
    5,
    178,
    137,
    2,
    59,
    70,
    18,
    24,
    31,
    25,
    13,
    49,
    166,
    58,
    47,
    23,
    57,
    38,
    106,
    40,
    4,
    50,
    55,
    24,
    18,
    70,
    33,
    94,
    69,
    60
  ],
  "cluster_centers": [
    {
      "x": 4.869478676612743,
      "y": 1.247269596021311
    },
    {
      "x": -6.56102116840471,
      "y": -7.11745631327573
    },
    {
      "x": -3.202708077039,
      "y": 8.708138282590161
    },
    {
      "x": -8.218132971708165,
      "y": 7.6867442233573575
    },
    {
      "x": -8.808131815841818,
      "y": 6.717609099717003
    },
    {
      "x": -9.008414225692139,
      "y": 7.515214814346448
    },
    {
      "x": 3.7779915992835065,
      "y": 1.6514477361985782
    },
    {
      "x": -3.014009341311441,
      "y": 9.705399047970811
    },
    {
      "x": -8.687289047459265,
      "y": 7.896053298387603
    },
    {
      "x": 4.614931270267789,
      "y": 2.541354828175252
    },
    {
      "x": -6.562814461510583,
      "y": -7.424526556108982
    },
    {
      "x": -9.298156023734322,
      "y": 7.617935506896059
    },
    {
      "x": 5.6987187923470275,
      "y": 1.969019930329939
    },
    {
      "x": 5.317825172593445,
      "y": 2.6755023532905047
    },
    {
      "x": 3.7820908472540062,
      "y": 2.317524695605726
    },
    {
      "x": -2.156771248646838,
      "y": 9.408348796851543
    },
    {
      "x": -2.204582754109619,
      "y": 9.844242121366145
    },
    {
      "x": -2.3073538328909606,
      "y": 8.481179993992372
    },
    {
      "x": -2.449880674400015,
      "y": 7.8280209603215205
    },
    {
      "x": -3.195283589766708,
      "y": 9.127702408251288
    },
    {
      "x": -3.457765471183269,
      "y": 9.629448977536686
    },
    {
      "x": -6.139150299800689,
      "y": -7.047740292890924
    },
    {
      "x": -6.373472521680704,
      "y": -7.8441632309008895
    },
    {
      "x": -7.037619022467941,
      "y": -7.291267681799173
    },
    {
      "x": -7.274498220618451,
      "y": -7.794275118461363
    },
    {
      "x": -7.470227550838659,
      "y": -6.369564689912655
    },
    {
      "x": -8.410610695783912,
      "y": 6.846859722871787
    },
    {
      "x": -9.414242660221595,
      "y": 6.938081081835585
    },
    {
      "x": 5.390273576387278,
      "y": 1.7290345254649815
    },
    {
      "x": 4.823212114026542,
      "y": 1.9759821990194404
    },
    {
      "x": 4.457224610492773,
      "y": 2.969339422183173
    },
    {
      "x": 3.9638551985865726,
      "y": 1.3700916554781897
    },
    {
      "x": -2.2797911211384028,
      "y": 8.801095809662247
    },
    {
      "x": -2.6046454926222635,
      "y": 9.372122153239399
    },
    {
      "x": -5.871587511496295,
      "y": -7.281291455278003
    },
    {
      "x": -6.685462236039092,
      "y": -7.7990118930323815
    },
    {
      "x": -6.728407930202219,
      "y": -6.015129304561166
    },
    {
      "x": -7.325366702326869,
      "y": -7.005633660863403
    },
    {
      "x": -8.716639282787007,
      "y": 5.9801275473310564
    },
    {
      "x": -8.853783947944471,
      "y": 8.54147062713037
    },
    {
      "x": -9.51293520356017,
      "y": 7.874413297493021
    },
    {
      "x": 6.2119580749067,
      "y": 0.6021895623952789
    },
    {
      "x": 5.808488837198698,
      "y": 1.3868396433853025
    },
    {
      "x": 4.572588498465482,
      "y": 1.6261839914472433
    },
    {
      "x": 4.0787921549033905,
      "y": 0.9402916213520973
    },
    {
      "x": -1.4564787871328875,
      "y": 9.86138774198424
    },
    {
      "x": -1.7244010249130741,
      "y": 9.316757375953156
    },
    {
      "x": -2.287646389884062,
      "y": 7.1083962685730215
    },
    {
      "x": -2.3676897748326255,
      "y": 10.480125391628253
    },
    {
      "x": -2.8908140321785147,
      "y": 8.345518023267552
    },
    {
      "x": -3.533723492671182,
      "y": 7.6533325874017955
    },
    {
      "x": -4.043742755773972,
      "y": 8.467533344881499
    },
    {
      "x": -6.416423370964997,
      "y": -6.567602086437833
    },
    {
      "x": -7.632848175838567,
      "y": -8.23297501881083
    },
    {
      "x": -7.667035214579179,
      "y": 6.463214241062781
    },
    {
      "x": -7.929339602459542,
      "y": 6.714944938363724
    },
    {
      "x": -8.181628624181634,
      "y": -6.210557572654695
    },
    {
      "x": -8.231933812249407,
      "y": 8.446320736972876
    },
    {
      "x": -9.360732141967482,
      "y": 8.59750024686868
    },
    {
      "x": -10.023940230933459,
      "y": 8.16857796423361
    },
    {
      "x": 5.131755512702877,
      "y": 3.4320785797688913
    },
    {
      "x": 4.203599815272097,
      "y": 2.7031677789955606
    },
    {
      "x": 3.7605500428385135,
      "y": 0.6334223328241512
    },
    {
      "x": 3.052398915553084,
      "y": 3.305977505110214
    },
    {
      "x": -0.6700594055072889,
      "y": 9.36541694309985
    },
    {
      "x": -3.40537907560255,
      "y": 8.386331108814074
    },
    {
      "x": -4.004641861228014,
      "y": 9.164305484600806
    },
    {
      "x": -5.080808845856951,
      "y": -5.717991213035657
    },
    {
      "x": -6.428078196689969,
      "y": -8.571533612997088
    },
    {
      "x": -7.366447363453421,
      "y": -5.892199508266983
    },
    {
      "x": -7.410023513505784,
      "y": 8.140424869191397
    },
    {
      "x": -8.176354442155938,
      "y": 9.330245111434651
    },
    {
      "x": -8.22431913230229,
      "y": 7.232903305028675
    },
    {
      "x": -8.65637594835396,
      "y": 8.211561224924472
    },
    {
      "x": -9.457847385482756,
      "y": 9.155038268948148
    },
    {
      "x": -9.736905532919009,
      "y": 7.13141282063889
    },
    {
      "x": -10.254759393293858,
      "y": 6.5430262300629165
    },
    {
      "x": 6.811371531592716,
      "y": 1.1853467598191316
    },
    {
      "x": 6.209021457661905,
      "y": 2.893624975458061
    },
    {
      "x": 5.525839092305066,
      "y": 2.2184904472482128
    },
    {
      "x": 4.578622592943484,
      "y": 3.3320499093724756
    },
    {
      "x": 3.2883602990661043,
      "y": 2.5894905767010368
    },
    {
      "x": 2.984964456421738,
      "y": 2.0471276524260342
    },
    {
      "x": -1.0374262162212151,
      "y": 8.64226286881823
    },
    {
      "x": -1.6911665583163207,
      "y": 7.7884321449958325
    },
    {
      "x": -1.8008479756487237,
      "y": 8.13101362259281
    },
    {
      "x": -2.496663909168897,
      "y": 10.000375072410778
    },
    {
      "x": -3.9372933022150094,
      "y": 8.185451504043407
    },
    {
      "x": -4.370071299717926,
      "y": -6.785889785281089
    },
    {
      "x": -4.481154524031075,
      "y": 9.094256347858426
    },
    {
      "x": -5.781158341658545,
      "y": -6.516600430418818
    },
    {
      "x": -5.976985034524709,
      "y": -5.566513116376392
    },
    {
      "x": -6.425412481889575,
      "y": 6.876669248818713
    },
    {
      "x": -6.528022311091213,
      "y": -4.904011287674194
    },
    {
      "x": -7.175008149506762,
      "y": -5.293602336339905
    },
    {
      "x": -7.332076799841974,
      "y": 7.388925173217997
    },
    {
      "x": -7.338289559775727,
      "y": 6.776719755047331
    },
    {
      "x": -7.724882172439272,
      "y": 5.81914927658833
    },
    {
      "x": -7.767308957052613,
      "y": -8.60997897954109
    },
    {
      "x": -7.804636283922537,
      "y": -7.135280825440683
    },
    {
      "x": -8.075129790132326,
      "y": -5.1265772805719525
    },
    {
      "x": -8.492644418473908,
      "y": -6.305424521413159
    },
    {
      "x": -8.61521963046082,
      "y": -5.367312277801048
    },
    {
      "x": -8.87238548832139,
      "y": 9.106202165075352
    },
    {
      "x": 7.718759644683339,
      "y": 3.0927445953753088
    },
    {
      "x": 6.772912210884368,
      "y": 0.021081884418230112
    },
    {
      "x": 6.7006267611100885,
      "y": 3.7285105263839364
    },
    {
      "x": 6.604603969144491,
      "y": 2.008433235912461
    },
    {
      "x": 6.2848465497293855,
      "y": 1.7241336443843536
    },
    {
      "x": 6.163002913497759,
      "y": 2.5120797276253906
    },
    {
      "x": 5.797989709728169,
      "y": 2.7648323779036676
    },
    {
      "x": 5.698303323077689,
      "y": 0.21443019751761772
    },
    {
      "x": 5.566056383759743,
      "y": 3.8825863244108625
    },
    {
      "x": 5.351493714316991,
      "y": 0.8485275921028628
    },
    {
      "x": 5.216435799283868,
      "y": 2.284419838484268
    },
    {
      "x": 4.981634812005261,
      "y": 3.8493405231566182
    },
    {
      "x": 4.364827139076457,
      "y": -0.32875148079485284
    },
    {
      "x": 3.8216581529946287,
      "y": 4.065556959626193
    },
    {
      "x": 3.4566203235623263,
      "y": -0.06606249381936857
    },
    {
      "x": 3.319645629207459,
      "y": 3.8046284497950857
    },
    {
      "x": 3.191794494730777,
      "y": 0.5657059095641768
    },
    {
      "x": 3.0454511774337343,
      "y": 1.3737946609869591
    },
    {
      "x": 2.5724367361882248,
      "y": 1.8840496444279435
    },
    {
      "x": 2.5159831119182945,
      "y": 1.447414662259971
    },
    {
      "x": 1.3986114961590288,
      "y": 0.9487820426064422
    },
    {
      "x": -0.19453905637924152,
      "y": 7.147020935606573
    },
    {
      "x": -0.36525353372742453,
      "y": 9.648205150516333
    },
    {
      "x": -0.38704142604011693,
      "y": 10.046751388749469
    },
    {
      "x": -0.9299848075453587,
      "y": 9.78172085735123
    },
    {
      "x": -1.106403312116651,
      "y": 7.612435065406041
    },
    {
      "x": -1.3506020440453461,
      "y": 8.19360380984661
    },
    {
      "x": -1.68713746305826,
      "y": 10.911079110852269
    },
    {
      "x": -1.6966718006585522,
      "y": 10.370526156769145
    },
    {
      "x": -1.8229374326782368,
      "y": 7.40157025700867
    },
    {
      "x": -1.9223405292524798,
      "y": 11.2047417540083
    },
    {
      "x": -1.9941499367467022,
      "y": 12.867017618853042
    },
    {
      "x": -2.4489674131117236,
      "y": 11.477528240683608
    },
    {
      "x": -2.773854456290706,
      "y": 11.73445529478794
    },
    {
      "x": -2.9013057761849077,
      "y": 7.550771180066203
    },
    {
      "x": -3.110904235282147,
      "y": 10.86656431270726
    },
    {
      "x": -3.4286218572865534,
      "y": 10.564220533215861
    },
    {
      "x": -5.128942727142494,
      "y": 9.836188632573545
    },
    {
      "x": -5.286440564511873,
      "y": -7.391325269707131
    },
    {
      "x": -5.633541998653641,
      "y": -8.953499825684096
    },
    {
      "x": -6.050221609967781,
      "y": -9.091244902283831
    },
    {
      "x": -6.246845325044985,
      "y": -4.609416735471551
    },
    {
      "x": -6.278243218367216,
      "y": 7.227463015774053
    },
    {
      "x": -6.349823013235987,
      "y": -5.438540972618046
    },
    {
      "x": -6.861208811961719,
      "y": -5.203672281000664
    },
    {
      "x": -6.9916907605883445,
      "y": 6.253438149172551
    },
    {
      "x": -7.0406412297864875,
      "y": 7.964365776765713
    },
    {
      "x": -7.110561721359948,
      "y": -6.183903228462528
    },
    {
      "x": -7.139218542514875,
      "y": -8.383252546394052
    },
    {
      "x": -7.287827263821933,
      "y": 6.325168874759912
    },
    {
      "x": -7.290822555305949,
      "y": 9.119400588594225
    },
    {
      "x": -7.771653067046857,
      "y": 8.492818505944376
    },
    {
      "x": -7.829026079983213,
      "y": -4.247727528438556
    },
    {
      "x": -7.8540053581594265,
      "y": 7.1095340712731945
    },
    {
      "x": -7.8555004441286025,
      "y": -5.826467796668107
    },
    {
      "x": -8.169588090892324,
      "y": -8.175188365339563
    },
    {
      "x": -8.216517794418813,
      "y": 5.753298195608247
    },
    {
      "x": -8.28713888586909,
      "y": -7.657926280866822
    },
    {
      "x": -8.358213436931111,
      "y": -5.7363555500690175
    },
    {
      "x": -8.507169629034433,
      "y": -6.832024646614564
    },
    {
      "x": -8.549159112728193,
      "y": 9.778823055409598
    },
    {
      "x": -8.588944072925255,
      "y": 8.900976195262178
    },
    {
      "x": -8.629944948688458,
      "y": 5.2817880470744125
    },
    {
      "x": -8.720501422482915,
      "y": -8.159686560011648
    },
    {
      "x": -8.750419112177125,
      "y": -7.231623077317256
    },
    {
      "x": -8.917751726329124,
      "y": -7.888195904193351
    },
    {
      "x": -8.961556599034992,
      "y": -5.183653224985909
    },
    {
      "x": -9.28451118985079,
      "y": 5.433982184553172
    },
    {
      "x": -9.290634075885087,
      "y": 4.899643588869747
    },
    {
      "x": -9.351271691278559,
      "y": -7.6770048487464235
    },
    {
      "x": -9.530596999544283,
      "y": -5.788602741353484
    },
    {
      "x": -9.576513834092841,
      "y": -6.934404459793758
    },
    {
      "x": -9.842468523388078,
      "y": 6.5557253503945745
    },
    {
      "x": -9.961049778198309,
      "y": 7.705932661682754
    },
    {
      "x": -10.089867180826454,
      "y": 8.767287519571962
    },
    {
      "x": -10.286341657052255,
      "y": 5.124716958878621
    }
  ],
  "n_clusters": 180
}